langchain_yt_dlp/__init__.py
langchain_yt_dlp/youtube_loader.py
langchain_yt_dlp-0.0.8.dist-info/LICENSE
langchain_yt_dlp-0.0.8.dist-info/METADATA
langchain_yt_dlp-0.0.8.dist-info/WHEEL
langchain_yt_dlp-0.0.8.dist-info/top_level.txt
langchain_yt_dlp-0.0.8.dist-info/RECORD
