Metadata-Version: 2.1
Name: langchain-yt-dlp
Version: 0.0.8
Summary: YouTube loader for LangChain using yt-dlp
Home-page: https://github.com/aqib0770/langchain-yt-dlp
Author: Aqib Ansari
Author-email: aqibansari72a@gmail.com
Keywords: langchain yt-dlp loader
Classifier: License :: OSI Approved :: MIT License
Classifier: Programming Language :: Python :: 3.8
Classifier: Programming Language :: Python :: 3.9
Classifier: Programming Language :: Python :: 3.10
Requires-Python: >=3.8
License-File: LICENSE
Requires-Dist: yt-dlp
Requires-Dist: langchain
